mbxai/__init__.py
mbxai/core.py
mbxai/agent/__init__.py
mbxai/agent/async_client.py
mbxai/agent/client.py
mbxai/agent/client_legacy.py
mbxai/agent/models.py
mbxai/examples/agent_example.py
mbxai/examples/agent_iterations_example.py
mbxai/examples/agent_logging_example.py
mbxai/examples/agent_tool_registration_example.py
mbxai/examples/agent_validation_example.py
mbxai/examples/auto_schema_example.py
mbxai/examples/conversation_history_test.py
mbxai/examples/dialog_agent_example.py
mbxai/examples/enhanced_agent_example.py
mbxai/examples/openrouter_example.py
mbxai/examples/optional_prompt_example.py
mbxai/examples/parse_example.py
mbxai/examples/parse_tool_example.py
mbxai/examples/redis_session_handler_example.py
mbxai/examples/request.json
mbxai/examples/response.json
mbxai/examples/send_request.py
mbxai/examples/simple_agent_test.py
mbxai/examples/tool_client_example.py
mbxai/examples/unified_interface_example.py
mbxai/examples/mcp/mcp_client_example.py
mbxai/examples/mcp/mcp_server_example.py
mbxai/image/__init__.py
mbxai/image/async_client.py
mbxai/image/models.py
mbxai/mcp/__init__.py
mbxai/mcp/async_client.py
mbxai/mcp/client.py
mbxai/mcp/example.py
mbxai/mcp/server.py
mbxai/openrouter/__init__.py
mbxai/openrouter/async_client.py
mbxai/openrouter/client.py
mbxai/openrouter/config.py
mbxai/openrouter/models.py
mbxai/openrouter/schema.py
mbxai/tools/__init__.py
mbxai/tools/async_client.py
mbxai/tools/client.py
mbxai/tools/example.py
mbxai/tools/types.py
mbxai/utils/__init__.py
mbxai/utils/client.py
mbxai-2.6.1.dist-info/METADATA
mbxai-2.6.1.dist-info/WHEEL
mbxai-2.6.1.dist-info/licenses/LICENSE
mbxai-2.6.1.dist-info/RECORD
