Metadata-Version: 2.4
Name: mbxai
Version: 2.6.1
Summary: MBX AI SDK
Project-URL: Homepage, https://www.mibexx.de
Project-URL: Documentation, https://www.mibexx.de
Project-URL: Repository, https://github.com/yourusername/mbxai.git
Author: MBX AI
License: MIT
License-File: LICENSE
Classifier: Development Status :: 4 - Beta
Classifier: Operating System :: OS Independent
Classifier: Programming Language :: Python
Classifier: Programming Language :: Python :: 3.12
Requires-Python: >=3.12
Requires-Dist: fastapi>=0.115.12
Requires-Dist: httpx>=0.27.0
Requires-Dist: mcp>=1.7.1
Requires-Dist: openai>=1.77.0
Requires-Dist: pydantic-settings>=2.9.1
Requires-Dist: pydantic>=2.9.1
Requires-Dist: python-multipart>=0.0.20
Requires-Dist: sse-starlette>=2.3.4
Requires-Dist: starlette>=0.46.2
Requires-Dist: typing-inspection<=0.4.0
Requires-Dist: uvicorn>=0.34.2
Provides-Extra: dev
Requires-Dist: black>=24.3.0; extra == 'dev'
Requires-Dist: isort>=5.13.2; extra == 'dev'
Requires-Dist: mypy>=1.8.0; extra == 'dev'
Requires-Dist: pytest-asyncio>=0.26.0; extra == 'dev'
Requires-Dist: pytest-cov>=6.1.1; extra == 'dev'
Requires-Dist: pytest>=8.3.5; extra == 'dev'
